smlr/__init__.py
smlr/cmlr.py
smlr/smlr.py
smlr/utils/functions.py
smlr_learn-0.1.2.dist-info/licenses/LICENSE
smlr_learn-0.1.2.dist-info/METADATA
smlr_learn-0.1.2.dist-info/WHEEL
smlr_learn-0.1.2.dist-info/top_level.txt
smlr_learn-0.1.2.dist-info/RECORD
