Metadata-Version: 2.4
Name: smlr-learn
Version: 0.1.2
Summary: Python Package of Simplex-based Multinomial Logistic Regression
Author-email: Zequan Xiong <xzqbear@foxmail.com>
Requires-Python: >=3.10
License-File: LICENSE
Requires-Dist: matplotlib>=3.10.7
Requires-Dist: numpy>=2.2.6
Requires-Dist: openpyxl>=3.1.5
Requires-Dist: pandas>=2.3.3
Requires-Dist: scikit-learn>=1.7.2
Dynamic: license-file
